[
    {
        "caption": "hexley is left of the ego car.",
        "image_file": "train/01222_03_im.jpg"
    },
    {
        "caption": "nolok is left of the ego car.",
        "image_file": "train/01222_03_im.jpg"
    },
    {
        "caption": "pidgin is in front of the ego car.",
        "image_file": "train/01222_03_im.jpg"
    },
    {
        "caption": "konqi is the ego car.",
        "image_file": "train/01222_03_im.jpg"
    },
    {
        "caption": "There are 4 karts in the scene.",
        "image_file": "train/01222_03_im.jpg"
    },
    {
        "caption": "The track is xr591.",
        "image_file": "train/01222_03_im.jpg"
    }
]