[
    {
        "caption": "tux is in front of the ego car.",
        "image_file": "train/012a1_02_im.jpg"
    },
    {
        "caption": "xue is right of the ego car.",
        "image_file": "train/012a1_02_im.jpg"
    },
    {
        "caption": "amanda is the ego car.",
        "image_file": "train/012a1_02_im.jpg"
    },
    {
        "caption": "There are 3 karts in the scene.",
        "image_file": "train/012a1_02_im.jpg"
    },
    {
        "caption": "The track is abyss.",
        "image_file": "train/012a1_02_im.jpg"
    }
]