[
    {
        "caption": "wilber is right of the ego car.",
        "image_file": "train/01464_07_im.jpg"
    },
    {
        "caption": "xue is right of the ego car.",
        "image_file": "train/01464_07_im.jpg"
    },
    {
        "caption": "gnu is the ego car.",
        "image_file": "train/01464_07_im.jpg"
    },
    {
        "caption": "There are 3 karts in the scene.",
        "image_file": "train/01464_07_im.jpg"
    },
    {
        "caption": "The track is scotland.",
        "image_file": "train/01464_07_im.jpg"
    }
]